scrapers/__init__.py
scrapers/scraper.py
scrapers/tiktok.py
tiktok_stats-0.0.2.dist-info/METADATA
tiktok_stats-0.0.2.dist-info/WHEEL
tiktok_stats-0.0.2.dist-info/top_level.txt
tiktok_stats-0.0.2.dist-info/RECORD
